<?xml version="1.0"?>
<!DOCTYPE ipe SYSTEM "ipe.dtd">
<ipe version="70218" creator="Ipe 7.2.24">
<info created="D:20221020151441" modified="D:20221020151441"/>
<ipestyle name="basic">
<symbol name="mark/disk(sx)" transformations="translations">
<path fill="sym-stroke">
0.6 0 0 0.6 0 0 e
</path>
</symbol>
<anglesize name="22.5 deg" value="22.5"/>
<anglesize name="30 deg" value="30"/>
<anglesize name="45 deg" value="45"/>
<anglesize name="60 deg" value="60"/>
<anglesize name="90 deg" value="90"/>
<arrowsize name="large" value="10"/>
<arrowsize name="small" value="5"/>
<arrowsize name="tiny" value="3"/>
<color name="blue" value="0 0 1"/>
<color name="gray" value="0.745"/>
<color name="green" value="0 1 0"/>
<color name="red" value="1 0 0"/>
<color name="yellow" value="1 1 0"/>
<pen name="normal" value="1"/>
<pen name="fat" value="1.2"/>
<pen name="heavier" value="0.8"/>
<pen name="ultrafat" value="2"/>
<gridsize name="16 pts (~6 mm)" value="16"/>
<gridsize name="32 pts (~12 mm)" value="32"/>
<gridsize name="4 pts" value="4"/>
<gridsize name="8 pts (~3 mm)" value="8"/>
<opacity name="10%" value="0.1"/>
<opacity name="25%" value="0.25"/>
<opacity name="50%" value="0.5"/>
<opacity name="75%" value="0.75"/>
<symbolsize name="large" value="5"/>
<symbolsize name="small" value="2"/>
<symbolsize name="tiny" value="1.1"/>
<textsize name="huge" value="\huge"/>
<textsize name="large" value="\large"/>
<textsize name="small" value="\small"/>
<textsize name="tiny" value="	iny"/>
<tiling name="falling" angle="-60" step="4" width="1"/>
<tiling name="rising" angle="30" step="4" width="1"/>
</ipestyle>
<page>
<layer name="edges"/>
<layer name="points"/>
<view layers="edges points" active="points"/>
<path layer="edges" stroke="black" pen="normal">
16.000000 300 m
576.000000 300 l
h
</path>
<path layer = "points" stroke = "black">
90.251012 300 m
-28.056680 0 0 28.056680 62.194332 300 34.137652 300 a
</path>
<path layer = "points" stroke = "black">
145.230769 300 m
-27.489879 0 0 27.489879 117.740891 300 90.251012 300 a
</path>
<path layer = "points" stroke = "black">
145.230769 300 m
-18.704453 0 0 18.704453 126.526316 300 107.821862 300 a
</path>
<path layer = "points" stroke = "black">
196.809717 300 m
-15.303644 0 0 15.303644 181.506073 300 166.202429 300 a
</path>
<path layer = "points" stroke = "black">
223.449393 300 m
-9.068826 0 0 9.068826 214.380567 300 205.311741 300 a
</path>
<path layer = "points" stroke = "black">
223.449393 300 m
-8.502024 0 0 8.502024 214.947368 300 206.445344 300 a
</path>
<path layer = "points" stroke = "black">
271.627530 300 m
-24.089069 0 0 24.089069 247.538462 300 223.449393 300 a
</path>
<path layer = "points" stroke = "black">
307.336032 300 m
-41.943320 0 0 41.943320 265.392713 300 223.449393 300 a
</path>
<path layer = "points" stroke = "black">
307.336032 300 m
-17.854251 0 0 17.854251 289.481781 300 271.627530 300 a
</path>
<path layer = "points" stroke = "black">
366.850202 300 m
-29.757085 0 0 29.757085 337.093117 300 307.336032 300 a
</path>
<path layer = "points" stroke = "black">
411.627530 300 m
-21.255061 0 0 21.255061 390.372470 300 369.117409 300 a
</path>
<path layer = "points" stroke = "black">
420.696356 300 m
-25.789474 0 0 25.789474 394.906883 300 369.117409 300 a
</path>
<path layer = "points" stroke = "black">
497.214575 300 m
-38.259109 0 0 38.259109 458.955466 300 420.696356 300 a
</path>
<path layer = "points" stroke = "black">
530.089069 300 m
-16.437247 0 0 16.437247 513.651822 300 497.214575 300 a
</path>
<path layer = "points" stroke = "black">
576.000000 300 m
-22.955466 0 0 22.955466 553.044534 300 530.089069 300 a
</path>
<path layer = "points" stroke = "black">
576.000000 300 m
-16.437247 0 0 16.437247 559.562753 300 543.125506 300 a
</path>
<path layer = "points" stroke = "black">
31.303644 300 m
-13.886640 0 0 13.886640 45.190283 300 59.076923 300 a
</path>
<path layer = "points" stroke = "black">
31.303644 300 m
-38.259109 0 0 38.259109 69.562753 300 107.821862 300 a
</path>
<path layer = "points" stroke = "black">
59.076923 300 m
-24.372470 0 0 24.372470 83.449393 300 107.821862 300 a
</path>
<path layer = "points" stroke = "black">
132.194332 300 m
-21.821862 0 0 21.821862 154.016194 300 175.838057 300 a
</path>
<path layer = "points" stroke = "black">
145.230769 300 m
-15.303644 0 0 15.303644 160.534413 300 175.838057 300 a
</path>
<path layer = "points" stroke = "black">
175.838057 300 m
-15.303644 0 0 15.303644 191.141700 300 206.445344 300 a
</path>
<path layer = "points" stroke = "black">
196.809717 300 m
-4.817814 0 0 4.817814 201.627530 300 206.445344 300 a
</path>
<path layer = "points" stroke = "black">
200.210526 300 m
-3.117409 0 0 3.117409 203.327935 300 206.445344 300 a
</path>
<path layer = "points" stroke = "black">
221.748988 300 m
-13.603239 0 0 13.603239 235.352227 300 248.955466 300 a
</path>
<path layer = "points" stroke = "black">
248.955466 300 m
-24.089069 0 0 24.089069 273.044534 300 297.133603 300 a
</path>
<path layer = "points" stroke = "black">
297.133603 300 m
-9.068826 0 0 9.068826 306.202429 300 315.271255 300 a
</path>
<path layer = "points" stroke = "black">
366.850202 300 m
-5.384615 0 0 5.384615 372.234818 300 377.619433 300 a
</path>
<path layer = "points" stroke = "black">
411.627530 300 m
-14.453441 0 0 14.453441 426.080972 300 440.534413 300 a
</path>
<path layer = "points" stroke = "black">
527.255061 300 m
-7.935223 0 0 7.935223 535.190283 300 543.125506 300 a
</path>
<use layer="points" name="mark/disk(sx)" pos="31.303644 300" size="normal" stroke="black"/><use layer="points" name="mark/disk(sx)" pos="34.137652 300" size="normal" stroke="black"/><use layer="points" name="mark/disk(sx)" pos="59.076923 300" size="normal" stroke="black"/><use layer="points" name="mark/disk(sx)" pos="90.251012 300" size="normal" stroke="black"/><use layer="points" name="mark/disk(sx)" pos="107.821862 300" size="normal" stroke="black"/><use layer="points" name="mark/disk(sx)" pos="132.194332 300" size="normal" stroke="black"/><use layer="points" name="mark/disk(sx)" pos="145.230769 300" size="normal" stroke="black"/><use layer="points" name="mark/disk(sx)" pos="166.202429 300" size="normal" stroke="black"/><use layer="points" name="mark/disk(sx)" pos="175.838057 300" size="normal" stroke="black"/><use layer="points" name="mark/disk(sx)" pos="196.809717 300" size="normal" stroke="black"/><use layer="points" name="mark/disk(sx)" pos="200.210526 300" size="normal" stroke="black"/><use layer="points" name="mark/disk(sx)" pos="205.311741 300" size="normal" stroke="black"/><use layer="points" name="mark/disk(sx)" pos="206.445344 300" size="normal" stroke="black"/><use layer="points" name="mark/disk(sx)" pos="221.748988 300" size="normal" stroke="black"/><use layer="points" name="mark/disk(sx)" pos="223.449393 300" size="normal" stroke="black"/><use layer="points" name="mark/disk(sx)" pos="248.955466 300" size="normal" stroke="black"/><use layer="points" name="mark/disk(sx)" pos="271.627530 300" size="normal" stroke="black"/><use layer="points" name="mark/disk(sx)" pos="297.133603 300" size="normal" stroke="black"/><use layer="points" name="mark/disk(sx)" pos="307.336032 300" size="normal" stroke="black"/><use layer="points" name="mark/disk(sx)" pos="315.271255 300" size="normal" stroke="black"/><use layer="points" name="mark/disk(sx)" pos="366.850202 300" size="normal" stroke="black"/><use layer="points" name="mark/disk(sx)" pos="369.117409 300" size="normal" stroke="black"/><use layer="points" name="mark/disk(sx)" pos="377.619433 300" size="normal" stroke="black"/><use layer="points" name="mark/disk(sx)" pos="411.627530 300" size="normal" stroke="black"/><use layer="points" name="mark/disk(sx)" pos="420.696356 300" size="normal" stroke="black"/><use layer="points" name="mark/disk(sx)" pos="440.534413 300" size="normal" stroke="black"/><use layer="points" name="mark/disk(sx)" pos="497.214575 300" size="normal" stroke="black"/><use layer="points" name="mark/disk(sx)" pos="527.255061 300" size="normal" stroke="black"/><use layer="points" name="mark/disk(sx)" pos="530.089069 300" size="normal" stroke="black"/><use layer="points" name="mark/disk(sx)" pos="543.125506 300" size="normal" stroke="black"/><use layer="points" name="mark/disk(sx)" pos="572.032389 300" size="normal" stroke="black"/><use layer="points" name="mark/disk(sx)" pos="576.000000 300" size="normal" stroke="black"/></page>
</ipe>
